{"appTeams":{"selectedTeamId":null,"teamsByIndex":[],"teamsToSignOut":[]},"bookmarks":[],"downloads":{"TLD2GNNT0":{"F042ZM2TN80":{"id":"F042ZM2TN80","teamId":"TLD2GNNT0","url":"https://files.slack.com/files-pri/TLD2GNNT0-F042ZM2TN80/download/image.png?origin_team=TLD2GNNT0","userId":"U040Y0D2C4E","appVersion":"4.28.171","downloadState":"completed","startTime":1663198012359,"progress":1,"downloadPath":"/home/paullarbs/Downloads/image.png","endTime":1663198012988}}},"enterprise":{},"settings":{"defaultSigninTeam":null,"hasRunApp":true,"hasRunFromTray":true,"isSignedIntoSlackOrg":false,"lastClogForProxyInfo":1664145369131,"suppressPermissionDialog":false,"whitelistedUrlSchemes":["http:","https:","mailto:","skype:","chrome-devtools:","devtools:","spotify:","live:","callto:","tel:","im:","sip:","sips:","slack:"],"allowedHostnames":{"ftp:":[],"sftp:":[],"ssh:":[],"smb:":[]},"allowedFileExts":[],"suppressMoveFromDmgDialog":false,"debugFeatures":[],"notificationAfterHoverTimeout":2000,"notificationFailover":0,"notificationFailoverEnabled":true,"notificationMaxItems":3,"notificationMethod":null,"notificationPlayback":"web","notificationPresentationCheck":null,"notificationTimeout":6000,"notificationZoomLevel":null,"notifyPosition":{"corner":"bottom_right","display":"same_as_app"},"forceHiddenInsetTitleBar":false,"isIAEnabled":true,"isClipboardReadDisabled":false,"isOpenExternalShellForced":true,"isTitleBarForcedByUser":false,"trafficLightPosition":{"x":14,"y":29},"autoHideMenuBar":false,"launchOnStartup":false,"keyboardLayout":"gb","locale":"en-GB","PrefSSBFileDownloadPath":"/home/paullarbs/Downloads","PrefSSBFileDownloadPathDisplayName":"Downloads","runFromTray":true,"startNetLogAtLaunch":false,"useHwAcceleration":true,"zoomLevel":0,"shouldUseHighContrastColors":false,"userTheme":"dark","systemThemeSyncEnabled":false,"releaseChannel":"prod","releaseChannelOverride":null,"hideOnStartup":true,"useTsLogBackend":false,"spellcheckerLanguage":"en-US","mainWindowSettings":{"fullScreen":false,"maximized":false,"bounds":{"x":-3271,"y":66,"width":1631,"height":1329}},"slackDefaults":{"defaultSigninTeam":null,"hasRunApp":false,"hasRunFromTray":false,"isSignedIntoSlackOrg":false,"lastClogForProxyInfo":0,"suppressPermissionDialog":false,"whitelistedUrlSchemes":["http:","https:","mailto:","skype:","chrome-devtools:","devtools:","spotify:","live:","callto:","tel:","im:","sip:","sips:","slack:"],"allowedHostnames":{"ftp:":[],"sftp:":[],"ssh:":[],"smb:":[]},"allowedFileExts":[],"suppressMoveFromDmgDialog":false,"debugFeatures":[],"notificationAfterHoverTimeout":2000,"notificationFailover":0,"notificationFailoverEnabled":true,"notificationMaxItems":3,"notificationMethod":null,"notificationPlayback":"web","notificationPresentationCheck":null,"notificationTimeout":6000,"notificationZoomLevel":null,"notifyPosition":{"corner":"bottom_right","display":"same_as_app"},"forceHiddenInsetTitleBar":false,"isIAEnabled":true,"isClipboardReadDisabled":false,"isOpenExternalShellForced":true,"isTitleBarForcedByUser":false,"trafficLightPosition":{"x":14,"y":22},"autoHideMenuBar":false,"launchOnStartup":null,"keyboardLayout":"","locale":"en-US","PrefSSBFileDownloadPath":"","PrefSSBFileDownloadPathDisplayName":"","runFromTray":true,"startNetLogAtLaunch":false,"useHwAcceleration":true,"zoomLevel":0,"shouldUseHighContrastColors":false,"userTheme":"light","systemThemeSyncEnabled":false,"releaseChannel":"prod","releaseChannelOverride":null,"hideOnStartup":true,"useTsLogBackend":false,"spellcheckerLanguage":"en-US"},"itDefaults":{},"userChoices":{"defaultSigninTeam":null,"hasRunApp":true,"hasRunFromTray":true,"isSignedIntoSlackOrg":false,"lastClogForProxyInfo":1664145369131,"suppressPermissionDialog":false,"whitelistedUrlSchemes":["http:","https:","mailto:","skype:","chrome-devtools:","devtools:","spotify:","live:","callto:","tel:","im:","sip:","sips:","slack:"],"allowedHostnames":{"ftp:":[],"sftp:":[],"ssh:":[],"smb:":[]},"allowedFileExts":[],"suppressMoveFromDmgDialog":false,"debugFeatures":[],"notificationAfterHoverTimeout":2000,"notificationFailover":0,"notificationFailoverEnabled":true,"notificationMaxItems":3,"notificationMethod":null,"notificationPlayback":"web","notificationPresentationCheck":null,"notificationTimeout":6000,"notificationZoomLevel":null,"notifyPosition":{"corner":"bottom_right","display":"same_as_app"},"forceHiddenInsetTitleBar":false,"isIAEnabled":true,"isClipboardReadDisabled":false,"isOpenExternalShellForced":true,"isTitleBarForcedByUser":false,"trafficLightPosition":{"x":14,"y":29},"autoHideMenuBar":false,"launchOnStartup":false,"keyboardLayout":"gb","locale":"en-GB","PrefSSBFileDownloadPath":"/home/paullarbs/Downloads","PrefSSBFileDownloadPathDisplayName":"Downloads","runFromTray":true,"startNetLogAtLaunch":false,"useHwAcceleration":true,"zoomLevel":0,"shouldUseHighContrastColors":false,"userTheme":"dark","systemThemeSyncEnabled":false,"releaseChannel":"prod","releaseChannelOverride":null,"hideOnStartup":true,"useTsLogBackend":false,"spellcheckerLanguage":"en-US","mainWindowSettings":{"fullScreen":false,"maximized":false,"bounds":{"x":-3271,"y":66,"width":1631,"height":1329}}},"itPolicy":{}},"teams":{},"webapp":{"teams":{"T01V94BKUDD":{"theme":{"titlebarBackground":"#121016","titlebarTextColor":"#D1D2D3"},"notificationPrefs":{"notificationSound":"knock_brush.mp3","noTextInNotifications":false,"muteSounds":false},"connectivityPrefs":{"ntlmCredentialDomains":"*"},"featureFlags":{"feature_desktop_reload_on_generic_error":true,"feature_desktop_restart_service_worker":false,"feature_desktop_extend_app_menu":true,"feature_desktop_enable_tslog":false,"feature_desktop_enable_sticky_notification_pref":false},"unreads":{"showBullet":true,"unreadHighlights":0,"unreads":0},"locale":"en-US","version":"1f400c19ff32412f46152bf6b958b9c67cf74105@1666057642","userId":"U040PSA23TR"},"TGCL6Q4LU":{"theme":{"titlebarBackground":"#121016","titlebarTextColor":"#D1D2D3"},"notificationPrefs":{"notificationSound":"knock_brush.mp3","noTextInNotifications":false,"muteSounds":false},"connectivityPrefs":{"ntlmCredentialDomains":"*"},"featureFlags":{"feature_desktop_reload_on_generic_error":true,"feature_desktop_restart_service_worker":false,"feature_desktop_extend_app_menu":true,"feature_desktop_enable_tslog":false,"feature_desktop_enable_sticky_notification_pref":false},"unreads":{"showBullet":true,"unreadHighlights":0,"unreads":0},"locale":"en-US","version":"1f400c19ff32412f46152bf6b958b9c67cf74105@1666057642","userId":"U040PS44RHD"},"TLD2GNNT0":{"theme":{"titlebarBackground":"#121016","titlebarTextColor":"#D1D2D3"},"notificationPrefs":{"notificationSound":"knock_brush.mp3","noTextInNotifications":false,"muteSounds":false},"connectivityPrefs":{"ntlmCredentialDomains":"*"},"featureFlags":{"feature_desktop_reload_on_generic_error":true,"feature_desktop_restart_service_worker":false,"feature_desktop_extend_app_menu":true,"feature_desktop_enable_tslog":false,"feature_desktop_enable_sticky_notification_pref":false},"unreads":{"showBullet":true,"unreadHighlights":0,"unreads":1},"locale":"en-GB","version":"1f400c19ff32412f46152bf6b958b9c67cf74105@1666057642","userId":"U040Y0D2C4E"}}},"workspaces":{"TLD2GNNT0":{"domain":"endeavour-drinks","id":"TLD2GNNT0","icon":{"image_68":"https://avatars.slack-edge.com/2020-10-14/1433015033940_1702ac913c10d09893ad_68.png","image_88":"https://avatars.slack-edge.com/2020-10-14/1433015033940_1702ac913c10d09893ad_88.png"},"name":"Endeavour Drinks","order":2},"T01V94BKUDD":{"domain":"supernovafriends","id":"T01V94BKUDD","icon":{"image_68":"https://avatars.slack-edge.com/2022-01-06/2913175551029_c3f4758adc02a008bb04_68.png","image_88":"https://avatars.slack-edge.com/2022-01-06/2913175551029_c3f4758adc02a008bb04_88.png"},"name":"Supernova Friends","order":0},"TGCL6Q4LU":{"domain":"bwsonline","id":"TGCL6Q4LU","icon":{"image_68":"https://a.slack-edge.com/80588/img/avatars-teams/ava_0016-68.png","image_88":"https://a.slack-edge.com/80588/img/avatars-teams/ava_0016-88.png"},"name":"BWS Online","order":1}},"workspacesMeta":{"selectedWorkspaceId":"TLD2GNNT0","selectedUserId":"U040Y0D2C4E"},"_persist":{"version":1,"rehydrated":true}}